MANIFEST.in
README.md
setup.py
KindleComicConverter.egg-info/PKG-INFO
KindleComicConverter.egg-info/SOURCES.txt
KindleComicConverter.egg-info/dependency_links.txt
KindleComicConverter.egg-info/entry_points.txt
KindleComicConverter.egg-info/not-zip-safe
KindleComicConverter.egg-info/requires.txt
KindleComicConverter.egg-info/top_level.txt
kindlecomicconverter/KCC_gui.py
kindlecomicconverter/KCC_rc.py
kindlecomicconverter/KCC_ui.py
kindlecomicconverter/KCC_ui_editor.py
kindlecomicconverter/__init__.py
kindlecomicconverter/comic2ebook.py
kindlecomicconverter/comic2panel.py
kindlecomicconverter/comicarchive.py
kindlecomicconverter/dualmetafix.py
kindlecomicconverter/image.py
kindlecomicconverter/kindle.py
kindlecomicconverter/metadata.py
kindlecomicconverter/pdfjpgextract.py
kindlecomicconverter/shared.py
kindlecomicconverter/startup.py