Metadata-Version: 1.0
Name: KindleComicConverter
Version: 5.5.2
Summary: Comic and Manga converter for e-book readers.
Home-page: http://github.com/ciromattia/kcc
Author: Ciro Mattia Gonano, Pawel Jastrzebski
Author-email: ciromattia@gmail.com, pawelj@iosphe.re
License: ISC License (ISCL)
Keywords: kindle,kobo,comic,manga,mobi,epub,cbz
Platform: UNKNOWN
